camera/__init__.py
camera/camera.py
handlers/__init__.py
handlers/detection_handler.py
image/__init__.py
image/image_handler.py
image/visualize.py
kml/__init__.py
kml/kml_handler.py
utils/__init__.py
utils/pkl.py
utils/polygon_handler.py
rpas_utils_lib-1.0.0.dist-info/METADATA
rpas_utils_lib-1.0.0.dist-info/WHEEL
rpas_utils_lib-1.0.0.dist-info/top_level.txt
rpas_utils_lib-1.0.0.dist-info/RECORD
