Metadata-Version: 2.1
Name: rpas_utils_lib
Version: 1.0.0
Summary: This library offers some utilities for Remotely Piloted Aircraft Systems (RPAS) services
Home-page: https://github.com/your_username/your_package
Author: Nuran Elsayed
Author-email: nuran@esbaar.com
Keywords: kml,visualize,detections,RPAS
Classifier: Development Status :: 3 - Alpha
Classifier: Programming Language :: Python :: 3
Classifier: License :: OSI Approved :: MIT License
Classifier: Operating System :: OS Independent
Requires-Dist: geopy ==2.3.0
Requires-Dist: httpx ==0.27.0
Requires-Dist: lxml ==4.9.2
Requires-Dist: numpy ==1.24.1
Requires-Dist: opencv-python ==4.8.0.74
Requires-Dist: pydantic ==1.10.4
Requires-Dist: PyExifTool ==0.5.5
Requires-Dist: pykml ==0.2.0
Requires-Dist: requests ==2.32.3
Requires-Dist: setuptools ==70.1.0
Requires-Dist: Shapely ==2.0.4
Requires-Dist: utm ==0.7.0
